arm_test_data/__init__.py
arm_test_data/dataset.py
arm_test_data/registry.txt
arm_test_data/version.py
arm_test_data-0.1.2.dist-info/licenses/LICENSE
arm_test_data-0.1.2.dist-info/METADATA
arm_test_data-0.1.2.dist-info/WHEEL
arm_test_data-0.1.2.dist-info/top_level.txt
arm_test_data-0.1.2.dist-info/RECORD
