Metadata-Version: 2.4
Name: arm-test-data
Version: 0.1.2
Summary: Provides utility functions for accessing data repository for ARM data examples/notebooks
Author: Atmospheric Data Community Toolkit Dev Team
License: MIT License
Project-URL: homepage, https://github.com/ARM-DOE/arm-test-data
Project-URL: documentation, https://github.com/ARM-DOE/arm-test-data
Project-URL: repository, https://github.com/ARM-DOE/arm-test-data
Project-URL: tracker, https://github.com/ARM-DOE/arm-test-data/issues
Keywords: arm-test-data,atmosphere,meteorology
Classifier: Development Status :: 2 - Pre-Alpha
Classifier: License :: OSI Approved :: MIT License
Classifier: Natural Language :: English
Classifier: Programming Language :: Python :: 3
Classifier: Programming Language :: Python :: 3.9
Classifier: Programming Language :: Python :: 3.10
Classifier: Programming Language :: Python :: 3.11
Classifier: Topic :: Scientific/Engineering
Classifier: Operating System :: OS Independent
Classifier: Intended Audience :: Science/Research
Requires-Python: >=3.8
License-File: LICENSE
Requires-Dist: pooch
Dynamic: license-file
